{
	"cmake" : 
	{
		"generator" : 
		{
			"multiConfig" : false,
			"name" : "MinGW Makefiles"
		},
		"paths" : 
		{
			"cmake" : "D:/Programs/mingw64/bin/cmake.exe",
			"cpack" : "D:/Programs/mingw64/bin/cpack.exe",
			"ctest" : "D:/Programs/mingw64/bin/ctest.exe",
			"root" : "D:/Programs/mingw64/share/cmake-3.28"
		},
		"version" : 
		{
			"isDirty" : false,
			"major" : 3,
			"minor" : 28,
			"patch" : 2,
			"string" : "3.28.2",
			"suffix" : ""
		}
	},
	"objects" : 
	[
		{
			"jsonFile" : "codemodel-v2-dbe0d6654f4b0406ce8a.json",
			"kind" : "codemodel",
			"version" : 
			{
				"major" : 2,
				"minor" : 6
			}
		},
		{
			"jsonFile" : "cache-v2-fccecb8985678079e013.json",
			"kind" : "cache",
			"version" : 
			{
				"major" : 2,
				"minor" : 0
			}
		},
		{
			"jsonFile" : "cmakeFiles-v1-e553f00fbc3c365aa140.json",
			"kind" : "cmakeFiles",
			"version" : 
			{
				"major" : 1,
				"minor" : 0
			}
		},
		{
			"jsonFile" : "toolchains-v1-80488b40c1f6c0364cb2.json",
			"kind" : "toolchains",
			"version" : 
			{
				"major" : 1,
				"minor" : 0
			}
		}
	],
	"reply" : 
	{
		"client-vscode" : 
		{
			"query.json" : 
			{
				"requests" : 
				[
					{
						"kind" : "cache",
						"version" : 2
					},
					{
						"kind" : "codemodel",
						"version" : 2
					},
					{
						"kind" : "toolchains",
						"version" : 1
					},
					{
						"kind" : "cmakeFiles",
						"version" : 1
					}
				],
				"responses" : 
				[
					{
						"jsonFile" : "cache-v2-fccecb8985678079e013.json",
						"kind" : "cache",
						"version" : 
						{
							"major" : 2,
							"minor" : 0
						}
					},
					{
						"jsonFile" : "codemodel-v2-dbe0d6654f4b0406ce8a.json",
						"kind" : "codemodel",
						"version" : 
						{
							"major" : 2,
							"minor" : 6
						}
					},
					{
						"jsonFile" : "toolchains-v1-80488b40c1f6c0364cb2.json",
						"kind" : "toolchains",
						"version" : 
						{
							"major" : 1,
							"minor" : 0
						}
					},
					{
						"jsonFile" : "cmakeFiles-v1-e553f00fbc3c365aa140.json",
						"kind" : "cmakeFiles",
						"version" : 
						{
							"major" : 1,
							"minor" : 0
						}
					}
				]
			}
		}
	}
}
